bitranox_coloredlogs/__init__.py
bitranox_coloredlogs/__init__.pyi
bitranox_coloredlogs/__init__conf__.py
bitranox_coloredlogs/cli.py
bitranox_coloredlogs/demo.py
bitranox_coloredlogs/py.typed
bitranox_coloredlogs/syslog.py
bitranox_coloredlogs/converter/__init__.py
bitranox_coloredlogs/converter/colors.py
bitranox_coloredlogs-14.0.9.dist-info/LICENSE
bitranox_coloredlogs-14.0.9.dist-info/LICENSE.txt
bitranox_coloredlogs-14.0.9.dist-info/METADATA
bitranox_coloredlogs-14.0.9.dist-info/WHEEL
bitranox_coloredlogs-14.0.9.dist-info/entry_points.txt
bitranox_coloredlogs-14.0.9.dist-info/top_level.txt
bitranox_coloredlogs-14.0.9.dist-info/RECORD
