Metadata-Version: 2.1
Name: bitranox-coloredlogs
Version: 14.0.9
Summary: fork of xolox coloredlogs with possibility to log to travis and jupyter
Home-page: https://github.com/bitranox/bitranox_coloredlogs
Author: Robert Nowotny
Author-email: bitranox@gmail.com
License: UNKNOWN
Platform: UNKNOWN
Classifier: Development Status :: 5 - Production/Stable
Classifier: Intended Audience :: Developers
Classifier: License :: OSI Approved :: MIT License
Classifier: Natural Language :: English
Classifier: Operating System :: OS Independent
Classifier: Programming Language :: Python
Classifier: Topic :: Software Development :: Libraries :: Python Modules
Requires-Python: >=3.6.0
Requires-Dist: click
Requires-Dist: humanfriendly (>=7.1)
